fast_ldp_mst_clustering/__init__.py
fast_ldp_mst_clustering/fast_ldp_mst_clustering.py
fast_ldp_mst_clustering-1.0.1.dist-info/LICENSE
fast_ldp_mst_clustering-1.0.1.dist-info/METADATA
fast_ldp_mst_clustering-1.0.1.dist-info/WHEEL
fast_ldp_mst_clustering-1.0.1.dist-info/top_level.txt
fast_ldp_mst_clustering-1.0.1.dist-info/RECORD
