Metadata-Version: 2.1
Name: fast-ldp-mst-clustering
Version: 1.0.1
Summary: Fast_LDP_MST is an efficient density-based clustering method for large-size datasets.
Home-page: https://github.com/Teng-Qiu-Clustering/Fast-LDP-MST-Clustering-IEEE-TKDE-2022
Author: Teng Qiu
Author-email: qiutengcool@163.com
Classifier: Programming Language :: Python :: 3
Classifier: License :: OSI Approved :: MIT License
Classifier: Operating System :: OS Independent
License-File: LICENSE
